real_ladybug/__init__.py
real_ladybug/_lbug.cpython-310-x86_64-linux-gnu.so
real_ladybug/async_connection.py
real_ladybug/connection.py
real_ladybug/constants.py
real_ladybug/database.py
real_ladybug/prepared_statement.py
real_ladybug/py.typed
real_ladybug/query_result.py
real_ladybug/torch_geometric_feature_store.py
real_ladybug/torch_geometric_graph_store.py
real_ladybug/torch_geometric_result_converter.py
real_ladybug/types.py
real_ladybug-0.14.1.dist-info/METADATA
real_ladybug-0.14.1.dist-info/WHEEL
real_ladybug-0.14.1.dist-info/top_level.txt
real_ladybug-0.14.1.dist-info/zip-safe
real_ladybug-0.14.1.dist-info/RECORD
real_ladybug-0.14.1.dist-info/licenses/LICENSE
