Metadata-Version: 2.4
Name: real_ladybug
Version: 0.14.1
Summary: Highly scalable, extremely fast, easy-to-use embeddable graph database
Home-page: https://github.com/lbugdb/lbug
License: MIT
Project-URL: Homepage, https://ladybugdb.com/
Project-URL: Documentation, https://docs.ladybugdb.com/
Project-URL: Repository, https://github.com/lbugdb/lbug
Project-URL: Changelog, https://github.com/LadybugDB/ladybug/releases
Keywords: graph,database
License-File: LICENSE
Provides-Extra: dev
Requires-Dist: networkx~=3.0; extra == "dev"
Requires-Dist: numpy~=2.0; extra == "dev"
Requires-Dist: pandas~=2.2; extra == "dev"
Requires-Dist: polars~=1.30; extra == "dev"
Requires-Dist: pyarrow~=20.0; extra == "dev"
Requires-Dist: pybind11~=2.13; extra == "dev"
Requires-Dist: pytest; extra == "dev"
Requires-Dist: pytest-asyncio~=1.0; extra == "dev"
Requires-Dist: setuptools~=80.9; extra == "dev"
Requires-Dist: ruff==0.11.12; extra == "dev"
Requires-Dist: mypy==1.16.0; extra == "dev"
Requires-Dist: torch>=2.5.0; extra == "dev"
Requires-Dist: torch-geometric>=2.5.0; extra == "dev"
Dynamic: license-file
